maskpw.py
maskpw-0.5.5.dist-info/LICENSE
maskpw-0.5.5.dist-info/WHEEL
maskpw-0.5.5.dist-info/METADATA
maskpw-0.5.5.dist-info/RECORD
