Metadata-Version: 2.1
Name: maskpw
Version: 0.5.5
Summary: A simple library to ask the user for a password. Similar to getpass.getpass() but allows to specify a default mask (like '*' instead of blank).
Author-email: harmony5 <jeancgo1@protonmail.com>
Requires-Python: ~=3.4
Classifier: License :: OSI Approved :: MIT License
Project-URL: Home, https://github.com/harmony5/maskpw
Project-URL: Source, https://github.com/harmony5/maskpw
